<?xml version="1.0" encoding="utf-8"?>
<extension version="2.5" type="plugin" group="redshop_product" method="upgrade">
    <name>redSHOP Shopper Group Conditional Tags</name>
    <author>redCOMPONENT.com</author>
    <version>1.3.2</version>
    <creationDate>April 2013</creationDate>
    <copyright>redCOMPONENT.com</copyright>
    <license>GNU/GPL</license>
    <authorEmail>email@redcomponent.com</authorEmail>
    <authorUrl>www.redweb.dk</authorUrl>
    <description>Manage redSHOP Product Tags Via Shopper Group Conditional Tags</description>
    <files>
        <filename plugin="shoppergroup_tags">shoppergroup_tags.php</filename>
    </files>
</extension>